README.md
setup.cfg
setup.py
app/__init__.py
app/cli.py
app/color.py
app/helpers.py
app/json_encoder.py
app/pixels_encoder.py
app/pixels_info.py
app/version.py
pixels_encoder.egg-info/PKG-INFO
pixels_encoder.egg-info/SOURCES.txt
pixels_encoder.egg-info/dependency_links.txt
pixels_encoder.egg-info/entry_points.txt
pixels_encoder.egg-info/not-zip-safe
pixels_encoder.egg-info/requires.txt
pixels_encoder.egg-info/top_level.txt