Metadata-Version: 1.0
Name: pixels-encoder
Version: 1.0.10
Summary: extract image pixels info into json
Home-page: https://github.com/app-craft/pixels-encoder
Author: sroik
Author-email: vasili.kazhanouski@gmail.com
License: MIT
Platform: UNKNOWN
